{
    "variable": [
        {
            "id": "baseUrl",
            "key": "baseUrl",
            "type": "string",
            "name": "string",
            "value": "http:\/\/localhost"
        }
    ],
    "info": {
        "name": "Laravel",
        "_postman_id": "e4146f69-cd8b-4e5b-bd0e-7f0e19118d65",
        "description": "",
        "schema": "https:\/\/schema.getpostman.com\/json\/collection\/v2.1.0\/collection.json"
    },
    "item": [
        {
            "name": "Endpoints",
            "description": "",
            "item": [
                {
                    "name": "POST api\/autenticar",
                    "request": {
                        "url": {
                            "host": "{{baseUrl}}",
                            "path": "api\/autenticar",
                            "query": [],
                            "raw": "{{baseUrl}}\/api\/autenticar"
                        },
                        "method": "POST",
                        "header": [
                            {
                                "key": "Content-Type",
                                "value": "application\/json"
                            },
                            {
                                "key": "Accept",
                                "value": "application\/json"
                            }
                        ],
                        "body": {
                            "mode": "raw",
                            "raw": "{\"email\":\"tremblay.eryn@example.com\",\"password\":\"v;$C!l\"}"
                        },
                        "description": "",
                        "auth": {
                            "type": "noauth"
                        }
                    },
                    "response": []
                },
                {
                    "name": "POST api\/registrar",
                    "request": {
                        "url": {
                            "host": "{{baseUrl}}",
                            "path": "api\/registrar",
                            "query": [],
                            "raw": "{{baseUrl}}\/api\/registrar"
                        },
                        "method": "POST",
                        "header": [
                            {
                                "key": "Content-Type",
                                "value": "application\/json"
                            },
                            {
                                "key": "Accept",
                                "value": "application\/json"
                            }
                        ],
                        "body": {
                            "mode": "raw",
                            "raw": "{\"name\":\"wfitrfzzwydsu\",\"email\":\"pinkie74@example.org\",\"password\":\"[cCt_6?zrWVpy?\"}"
                        },
                        "description": "",
                        "auth": {
                            "type": "noauth"
                        }
                    },
                    "response": []
                },
                {
                    "name": "POST api\/v1\/sair",
                    "request": {
                        "url": {
                            "host": "{{baseUrl}}",
                            "path": "api\/v1\/sair",
                            "query": [],
                            "raw": "{{baseUrl}}\/api\/v1\/sair"
                        },
                        "method": "POST",
                        "header": [
                            {
                                "key": "Content-Type",
                                "value": "application\/json"
                            },
                            {
                                "key": "Accept",
                                "value": "application\/json"
                            }
                        ],
                        "body": null,
                        "description": "",
                        "auth": {
                            "type": "noauth"
                        }
                    },
                    "response": []
                },
                {
                    "name": "GET api\/v1\/autores\/listar",
                    "request": {
                        "url": {
                            "host": "{{baseUrl}}",
                            "path": "api\/v1\/autores\/listar",
                            "query": [],
                            "raw": "{{baseUrl}}\/api\/v1\/autores\/listar"
                        },
                        "method": "GET",
                        "header": [
                            {
                                "key": "Content-Type",
                                "value": "application\/json"
                            },
                            {
                                "key": "Accept",
                                "value": "application\/json"
                            }
                        ],
                        "body": null,
                        "description": "",
                        "auth": {
                            "type": "noauth"
                        }
                    },
                    "response": [
                        {
                            "header": [
                                {
                                    "key": "cache-control",
                                    "value": "no-cache, private"
                                },
                                {
                                    "key": "content-type",
                                    "value": "application\/json"
                                },
                                {
                                    "key": "x-ratelimit-limit",
                                    "value": "60"
                                },
                                {
                                    "key": "x-ratelimit-remaining",
                                    "value": "59"
                                },
                                {
                                    "key": "access-control-allow-origin",
                                    "value": "*"
                                }
                            ],
                            "code": 401,
                            "body": "{\"error\":\"Bearer token no cabe\\u00e7alho \\u00e9 obrigat\\u00f3rio.\"}",
                            "name": ""
                        }
                    ]
                },
                {
                    "name": "POST api\/v1\/autores\/criar",
                    "request": {
                        "url": {
                            "host": "{{baseUrl}}",
                            "path": "api\/v1\/autores\/criar",
                            "query": [],
                            "raw": "{{baseUrl}}\/api\/v1\/autores\/criar"
                        },
                        "method": "POST",
                        "header": [
                            {
                                "key": "Content-Type",
                                "value": "application\/json"
                            },
                            {
                                "key": "Accept",
                                "value": "application\/json"
                            }
                        ],
                        "body": {
                            "mode": "raw",
                            "raw": "{\"nome\":\"phpjkyuogsufwcvib\",\"data_nascimento\":\"msvfohyvwru\"}"
                        },
                        "description": "",
                        "auth": {
                            "type": "noauth"
                        }
                    },
                    "response": []
                },
                {
                    "name": "PUT api\/v1\/autores\/atualizar",
                    "request": {
                        "url": {
                            "host": "{{baseUrl}}",
                            "path": "api\/v1\/autores\/atualizar",
                            "query": [],
                            "raw": "{{baseUrl}}\/api\/v1\/autores\/atualizar"
                        },
                        "method": "PUT",
                        "header": [
                            {
                                "key": "Content-Type",
                                "value": "application\/json"
                            },
                            {
                                "key": "Accept",
                                "value": "application\/json"
                            }
                        ],
                        "body": {
                            "mode": "raw",
                            "raw": "{\"nome\":\"bjzfz\",\"data_nascimento\":\"vjxoohvvbrhbjubdpirfpfuebdminlapqphvyqwfsykuzk\"}"
                        },
                        "description": "",
                        "auth": {
                            "type": "noauth"
                        }
                    },
                    "response": []
                },
                {
                    "name": "DELETE api\/v1\/autores\/deletar\/{id}",
                    "request": {
                        "url": {
                            "host": "{{baseUrl}}",
                            "path": "api\/v1\/autores\/deletar\/:id",
                            "query": [],
                            "raw": "{{baseUrl}}\/api\/v1\/autores\/deletar\/:id",
                            "variable": [
                                {
                                    "id": "id",
                                    "key": "id",
                                    "value": "voluptate",
                                    "description": "The ID of the deletar."
                                }
                            ]
                        },
                        "method": "DELETE",
                        "header": [
                            {
                                "key": "Content-Type",
                                "value": "application\/json"
                            },
                            {
                                "key": "Accept",
                                "value": "application\/json"
                            }
                        ],
                        "body": null,
                        "description": "",
                        "auth": {
                            "type": "noauth"
                        }
                    },
                    "response": []
                },
                {
                    "name": "GET api\/v1\/livros\/listar",
                    "request": {
                        "url": {
                            "host": "{{baseUrl}}",
                            "path": "api\/v1\/livros\/listar",
                            "query": [],
                            "raw": "{{baseUrl}}\/api\/v1\/livros\/listar"
                        },
                        "method": "GET",
                        "header": [
                            {
                                "key": "Content-Type",
                                "value": "application\/json"
                            },
                            {
                                "key": "Accept",
                                "value": "application\/json"
                            }
                        ],
                        "body": null,
                        "description": "",
                        "auth": {
                            "type": "noauth"
                        }
                    },
                    "response": [
                        {
                            "header": [
                                {
                                    "key": "cache-control",
                                    "value": "no-cache, private"
                                },
                                {
                                    "key": "content-type",
                                    "value": "application\/json"
                                },
                                {
                                    "key": "x-ratelimit-limit",
                                    "value": "60"
                                },
                                {
                                    "key": "x-ratelimit-remaining",
                                    "value": "58"
                                },
                                {
                                    "key": "access-control-allow-origin",
                                    "value": "*"
                                }
                            ],
                            "code": 401,
                            "body": "{\"error\":\"Bearer token no cabe\\u00e7alho \\u00e9 obrigat\\u00f3rio.\"}",
                            "name": ""
                        }
                    ]
                },
                {
                    "name": "POST api\/v1\/livros\/criar",
                    "request": {
                        "url": {
                            "host": "{{baseUrl}}",
                            "path": "api\/v1\/livros\/criar",
                            "query": [],
                            "raw": "{{baseUrl}}\/api\/v1\/livros\/criar"
                        },
                        "method": "POST",
                        "header": [
                            {
                                "key": "Content-Type",
                                "value": "application\/json"
                            },
                            {
                                "key": "Accept",
                                "value": "application\/json"
                            }
                        ],
                        "body": {
                            "mode": "raw",
                            "raw": "{\"titulo\":\"afelurojmbttavhtgrjweqj\",\"ano_publicacao\":4}"
                        },
                        "description": "",
                        "auth": {
                            "type": "noauth"
                        }
                    },
                    "response": []
                },
                {
                    "name": "PUT api\/v1\/livros\/atualizar",
                    "request": {
                        "url": {
                            "host": "{{baseUrl}}",
                            "path": "api\/v1\/livros\/atualizar",
                            "query": [],
                            "raw": "{{baseUrl}}\/api\/v1\/livros\/atualizar"
                        },
                        "method": "PUT",
                        "header": [
                            {
                                "key": "Content-Type",
                                "value": "application\/json"
                            },
                            {
                                "key": "Accept",
                                "value": "application\/json"
                            }
                        ],
                        "body": {
                            "mode": "raw",
                            "raw": "{\"titulo\":\"wwixyqerhew\",\"ano_publicacao\":32}"
                        },
                        "description": "",
                        "auth": {
                            "type": "noauth"
                        }
                    },
                    "response": []
                },
                {
                    "name": "DELETE api\/v1\/livros\/deletar\/{id}",
                    "request": {
                        "url": {
                            "host": "{{baseUrl}}",
                            "path": "api\/v1\/livros\/deletar\/:id",
                            "query": [],
                            "raw": "{{baseUrl}}\/api\/v1\/livros\/deletar\/:id",
                            "variable": [
                                {
                                    "id": "id",
                                    "key": "id",
                                    "value": "aut",
                                    "description": "The ID of the deletar."
                                }
                            ]
                        },
                        "method": "DELETE",
                        "header": [
                            {
                                "key": "Content-Type",
                                "value": "application\/json"
                            },
                            {
                                "key": "Accept",
                                "value": "application\/json"
                            }
                        ],
                        "body": null,
                        "description": "",
                        "auth": {
                            "type": "noauth"
                        }
                    },
                    "response": []
                },
                {
                    "name": "GET api\/v1\/emprestimos\/listar",
                    "request": {
                        "url": {
                            "host": "{{baseUrl}}",
                            "path": "api\/v1\/emprestimos\/listar",
                            "query": [],
                            "raw": "{{baseUrl}}\/api\/v1\/emprestimos\/listar"
                        },
                        "method": "GET",
                        "header": [
                            {
                                "key": "Content-Type",
                                "value": "application\/json"
                            },
                            {
                                "key": "Accept",
                                "value": "application\/json"
                            }
                        ],
                        "body": null,
                        "description": "",
                        "auth": {
                            "type": "noauth"
                        }
                    },
                    "response": [
                        {
                            "header": [
                                {
                                    "key": "cache-control",
                                    "value": "no-cache, private"
                                },
                                {
                                    "key": "content-type",
                                    "value": "application\/json"
                                },
                                {
                                    "key": "x-ratelimit-limit",
                                    "value": "60"
                                },
                                {
                                    "key": "x-ratelimit-remaining",
                                    "value": "57"
                                },
                                {
                                    "key": "access-control-allow-origin",
                                    "value": "*"
                                }
                            ],
                            "code": 401,
                            "body": "{\"error\":\"Bearer token no cabe\\u00e7alho \\u00e9 obrigat\\u00f3rio.\"}",
                            "name": ""
                        }
                    ]
                },
                {
                    "name": "POST api\/v1\/emprestimos\/registrar",
                    "request": {
                        "url": {
                            "host": "{{baseUrl}}",
                            "path": "api\/v1\/emprestimos\/registrar",
                            "query": [],
                            "raw": "{{baseUrl}}\/api\/v1\/emprestimos\/registrar"
                        },
                        "method": "POST",
                        "header": [
                            {
                                "key": "Content-Type",
                                "value": "application\/json"
                            },
                            {
                                "key": "Accept",
                                "value": "application\/json"
                            }
                        ],
                        "body": {
                            "mode": "raw",
                            "raw": "{\"user_id\":17,\"livro_id\":2,\"data_emprestimo\":\"gujvqwyorhlivcufsdftwxxyumanimakramitghrswquaoatdrjgxqyvpgzwythbmctoknrgbphhgshv\",\"data_devolucao\":\"gjdjjpwlufshjormhvsk\",\"email\":\"ilene07@example.com\",\"nome\":\"rhfhfdkdtlmtutuyz\",\"mensagem\":\"jhtpq\"}"
                        },
                        "description": "",
                        "auth": {
                            "type": "noauth"
                        }
                    },
                    "response": []
                }
            ]
        }
    ],
    "auth": {
        "type": "noauth"
    }
}